gf_inst_client/__init__.py
gf_inst_client/client.py
gf_inst_client/conditions.py
gf_inst_client-1.1.1.dist-info/licenses/LICENSE.txt
gf_inst_client-1.1.1.dist-info/METADATA
gf_inst_client-1.1.1.dist-info/WHEEL
gf_inst_client-1.1.1.dist-info/top_level.txt
gf_inst_client-1.1.1.dist-info/RECORD
