Metadata-Version: 2.4
Name: gf_inst_client
Version: 1.1.1
Summary: 广发证券开放平台 API 客户端
Author: gf_gaoxinzhe
Author-email: gao89622@163.com
Classifier: Programming Language :: Python :: 3
Classifier: License :: OSI Approved :: MIT License
Classifier: Operating System :: OS Independent
Requires-Python: >=3.6
License-File: LICENSE.txt
Requires-Dist: requests>=2.31.0
Requires-Dist: pandas>=2.0.0
Dynamic: author
Dynamic: author-email
Dynamic: classifier
Dynamic: description
Dynamic: description-content-type
Dynamic: license-file
Dynamic: requires-dist
Dynamic: requires-python
Dynamic: summary
